{"id": "alternativemediatelevisionamtv--2020-06-05--THE RE-OPENING OF AMERICA!! END OF THE MIDDLE CLASS\u2026", "date": "2020-06-05", "source": "alternativemediatelevisionamtv", "title": "THE RE-OPENING OF AMERICA!! END OF THE MIDDLE CLASS\u2026", "content": "THE RE-OPENING OF AMERICA !\n!\nEND OF THE MIDDLE CLASS\u2026 In today \u2019 s video , AMTV reports on @ @ @ @ @ United States 2020 .", "author": "Christopher Greene", "url": "https://www.amtvmedia.com/the-re-opening-of-america-end-of-the-middle-class/", "published": "Fri, 05 Jun 2020 22:28:25 +0000", "published_utc": 1591410505, "collection_utc": 1591403478}