{"id": "alternativemediatelevisionamtv--2020-03-07--USA ALERT!!! MANDATORY QUARANTINE IN EFFECT!!!", "date": "2020-03-07", "source": "alternativemediatelevisionamtv", "title": "USA ALERT!!! MANDATORY QUARANTINE IN EFFECT!!!", "content": "Get live updates and video completely uncensored and delivered to your inbox !", "author": "Christopher Greene", "url": "https://www.amtvmedia.com/usa-alert-mandatory-quarantine-in-effect/", "published": "Sat, 07 Mar 2020 00:08:29 +0000", "published_utc": 1583557709, "collection_utc": 1584248158}